{
    "/js/app.js": "/js/app.js",
    "/css/app.css": "/css/app.css",
    "/FreeResponseStatistics.js": "/FreeResponseStatistics.js",
    "/ImageResponseStatistics.js": "/ImageResponseStatistics.js",
    "/QuestionForm.js": "/QuestionForm.js",
    "/folder.js": "/folder.js",
    "/multiplechoicestatistics.js": "/multiplechoicestatistics.js",
    "/vendors~FreeResponseStatistics.js": "/vendors~FreeResponseStatistics.js",
    "/vendors~ImageResponseStatistics.js": "/vendors~ImageResponseStatistics.js",
    "/vendors~QuestionForm.js": "/vendors~QuestionForm.js",
    "/vendors~folder.js": "/vendors~folder.js",
    "/js/app.0b303c1ddccab0f35e92.hot-update.js": "/js/app.0b303c1ddccab0f35e92.hot-update.js",
    "/js/app.c18fb4c87c0a07fdd8d8.hot-update.js": "/js/app.c18fb4c87c0a07fdd8d8.hot-update.js"
}
