{
    "/js/app.js": "/js/app.js",
    "/css/app.css": "/css/app.css",
    "/FreeResponseStatistics.js": "/FreeResponseStatistics.js",
    "/ImageResponseStatistics.js": "/ImageResponseStatistics.js",
    "/QuestionForm.js": "/QuestionForm.js",
    "/folder.js": "/folder.js",
    "/multiplechoicestatistics.js": "/multiplechoicestatistics.js",
    "/vendors~FreeResponseStatistics.js": "/vendors~FreeResponseStatistics.js",
    "/vendors~ImageResponseStatistics.js": "/vendors~ImageResponseStatistics.js",
    "/vendors~QuestionForm.js": "/vendors~QuestionForm.js",
    "/vendors~folder.js": "/vendors~folder.js",
    "/folder.9af4e9289d6b34b75fde.hot-update.js": "/folder.9af4e9289d6b34b75fde.hot-update.js"
}
