{
    "/js/app.js": "/js/app.js",
    "/css/app.css": "/css/app.css",
    "/FreeResponseStatistics.js": "/FreeResponseStatistics.js",
    "/ImageResponseStatistics.js": "/ImageResponseStatistics.js",
    "/QuestionForm.js": "/QuestionForm.js",
    "/folder.js": "/folder.js",
    "/multiplechoicestatistics.js": "/multiplechoicestatistics.js",
    "/vendors~FreeResponseStatistics.js": "/vendors~FreeResponseStatistics.js",
    "/vendors~FreeResponseStatistics~ImageResponseStatistics~folder~multiplechoicestatistics.js": "/vendors~FreeResponseStatistics~ImageResponseStatistics~folder~multiplechoicestatistics.js",
    "/vendors~ImageResponseStatistics.js": "/vendors~ImageResponseStatistics.js",
    "/vendors~QuestionForm.js": "/vendors~QuestionForm.js",
    "/js/app.3ff83a07c0037dc1ab98.hot-update.js": "/js/app.3ff83a07c0037dc1ab98.hot-update.js",
    "/js/app.9d6457cff9b4ce964cb5.hot-update.js": "/js/app.9d6457cff9b4ce964cb5.hot-update.js",
    "/js/app.49434195b40b921f3cc3.hot-update.js": "/js/app.49434195b40b921f3cc3.hot-update.js",
    "/js/app.397155dcda84653d0fe8.hot-update.js": "/js/app.397155dcda84653d0fe8.hot-update.js",
    "/js/app.e545deb04f921c339076.hot-update.js": "/js/app.e545deb04f921c339076.hot-update.js",
    "/js/app.969811a23198148025de.hot-update.js": "/js/app.969811a23198148025de.hot-update.js",
    "/js/app.b61b1d3c3a22247c127e.hot-update.js": "/js/app.b61b1d3c3a22247c127e.hot-update.js",
    "/js/app.44df973daf3765603400.hot-update.js": "/js/app.44df973daf3765603400.hot-update.js",
    "/js/app.a4e2de62c6da1d7e4f2a.hot-update.js": "/js/app.a4e2de62c6da1d7e4f2a.hot-update.js",
    "/js/app.e78e2fe950841caee3e7.hot-update.js": "/js/app.e78e2fe950841caee3e7.hot-update.js",
    "/js/app.033ed855f05c5bb35b7d.hot-update.js": "/js/app.033ed855f05c5bb35b7d.hot-update.js",
    "/js/app.d2b2fa2ce4bb1b201a1d.hot-update.js": "/js/app.d2b2fa2ce4bb1b201a1d.hot-update.js",
    "/js/app.4e674ae0e09fb9f22c6f.hot-update.js": "/js/app.4e674ae0e09fb9f22c6f.hot-update.js",
    "/js/app.456b7ebbfd646bbbac5f.hot-update.js": "/js/app.456b7ebbfd646bbbac5f.hot-update.js",
    "/js/app.0bf6a08002f1095d26b0.hot-update.js": "/js/app.0bf6a08002f1095d26b0.hot-update.js",
    "/js/app.01232d616c9cdd54db78.hot-update.js": "/js/app.01232d616c9cdd54db78.hot-update.js",
    "/js/app.9d712845abdd8563f6a2.hot-update.js": "/js/app.9d712845abdd8563f6a2.hot-update.js",
    "/js/app.ad0b2f4f857f10daf117.hot-update.js": "/js/app.ad0b2f4f857f10daf117.hot-update.js",
    "/js/app.7ee8c8aa4de065e3103c.hot-update.js": "/js/app.7ee8c8aa4de065e3103c.hot-update.js",
    "/js/app.dd5b154d780b0110f39e.hot-update.js": "/js/app.dd5b154d780b0110f39e.hot-update.js",
    "/js/app.cf3749a417d1ef13420a.hot-update.js": "/js/app.cf3749a417d1ef13420a.hot-update.js",
    "/js/app.edd3e48d05a817d32393.hot-update.js": "/js/app.edd3e48d05a817d32393.hot-update.js",
    "/js/app.cb860851ec2cab9d7430.hot-update.js": "/js/app.cb860851ec2cab9d7430.hot-update.js",
    "/js/app.9796ea9676d81bab925d.hot-update.js": "/js/app.9796ea9676d81bab925d.hot-update.js",
    "/js/app.16173ab61df43b59e6f5.hot-update.js": "/js/app.16173ab61df43b59e6f5.hot-update.js",
    "/js/app.2f32556c26d610dc9b38.hot-update.js": "/js/app.2f32556c26d610dc9b38.hot-update.js",
    "/js/app.1db746fa528e21caf002.hot-update.js": "/js/app.1db746fa528e21caf002.hot-update.js",
    "/js/app.de974a63a5f53db99514.hot-update.js": "/js/app.de974a63a5f53db99514.hot-update.js",
    "/js/app.2491057bc2fd9dc191e7.hot-update.js": "/js/app.2491057bc2fd9dc191e7.hot-update.js",
    "/js/app.4f889de3bca76a4a8316.hot-update.js": "/js/app.4f889de3bca76a4a8316.hot-update.js",
    "/js/app.4cfdbb959cb63077f850.hot-update.js": "/js/app.4cfdbb959cb63077f850.hot-update.js",
    "/js/app.3c6772a642f65364a140.hot-update.js": "/js/app.3c6772a642f65364a140.hot-update.js",
    "/js/app.6ae831c31c5bbd19d05c.hot-update.js": "/js/app.6ae831c31c5bbd19d05c.hot-update.js",
    "/js/app.2466c53d21ff7fd0a5e2.hot-update.js": "/js/app.2466c53d21ff7fd0a5e2.hot-update.js",
    "/js/app.3e03514b0406ed5b593c.hot-update.js": "/js/app.3e03514b0406ed5b593c.hot-update.js",
    "/js/app.5be853ef43150b619763.hot-update.js": "/js/app.5be853ef43150b619763.hot-update.js",
    "/js/app.008126c3e4e037cec6b1.hot-update.js": "/js/app.008126c3e4e037cec6b1.hot-update.js",
    "/js/app.694f078ddba611293f77.hot-update.js": "/js/app.694f078ddba611293f77.hot-update.js",
    "/js/app.765140881b291b417ee7.hot-update.js": "/js/app.765140881b291b417ee7.hot-update.js",
    "/js/app.72ada57b0a77b75ff515.hot-update.js": "/js/app.72ada57b0a77b75ff515.hot-update.js",
    "/js/app.a1c7b475617a13ec994b.hot-update.js": "/js/app.a1c7b475617a13ec994b.hot-update.js",
    "/js/app.e1d047f4f5967a85d6c9.hot-update.js": "/js/app.e1d047f4f5967a85d6c9.hot-update.js",
    "/js/app.4b57f68804270f2b175d.hot-update.js": "/js/app.4b57f68804270f2b175d.hot-update.js",
    "/js/app.a25e621fa95a2b02eac8.hot-update.js": "/js/app.a25e621fa95a2b02eac8.hot-update.js",
    "/js/app.f75b389b2a24316ae4d6.hot-update.js": "/js/app.f75b389b2a24316ae4d6.hot-update.js",
    "/js/app.7080eae2f9bb15c11906.hot-update.js": "/js/app.7080eae2f9bb15c11906.hot-update.js",
    "/js/app.251370f1afa0eca38f87.hot-update.js": "/js/app.251370f1afa0eca38f87.hot-update.js",
    "/js/app.cfdb6ab955effef553df.hot-update.js": "/js/app.cfdb6ab955effef553df.hot-update.js",
    "/js/app.d416858227afea47368b.hot-update.js": "/js/app.d416858227afea47368b.hot-update.js",
    "/js/app.6c1273219628a6b54922.hot-update.js": "/js/app.6c1273219628a6b54922.hot-update.js",
    "/js/app.3fc27861e919321f9f77.hot-update.js": "/js/app.3fc27861e919321f9f77.hot-update.js"
}
